pic_rucio-2024.10.3.71620.data/scripts/pic_rucio
transfer_agents/__init__.py
transfer_agents/config.py
transfer_agents/db_functions.py
transfer_agents/es_query.py
transfer_agents/metadata.py
transfer_agents/rucio_functions.py
transfer_agents/transfer_file.py
transfer_agents/config_files/config.yaml
transfer_agents/config_files/es_body.json
transfer_agents/config_files/logger.yaml
transfer_agents/config_files/magic.yaml
transfer_agents/config_files/magic_metadata.yaml
transfer_agents/config_files/metadata.yaml
transfer_agents/config_files/rucio.cfg.atlas.client.template
transfer_agents/config_files/rucio.yaml
transfer_agents/config_files/sample.yaml
transfer_agents/config_files/sample_nondet.yaml
transfer_agents/config_files/transfer.csv
pic_rucio-2024.10.3.71620.dist-info/LICENSE
pic_rucio-2024.10.3.71620.dist-info/METADATA
pic_rucio-2024.10.3.71620.dist-info/WHEEL
pic_rucio-2024.10.3.71620.dist-info/top_level.txt
pic_rucio-2024.10.3.71620.dist-info/RECORD
