Metadata-Version: 2.1
Name: pic_rucio
Version: 2024.10.3.71620
Summary: PIC rucio client transfer package
Home-page: https://gitlab.pic.es/rucio/rucio-client
Author: Agustin Bruzzese
Author-email: bruzzese@pic.es
Classifier: Development Status :: 5 - Production/Stable
Classifier: License :: OSI Approved :: Apache Software License
Classifier: Intended Audience :: Information Technology
Classifier: Intended Audience :: System Administrators
Classifier: Operating System :: POSIX :: Linux
Classifier: Natural Language :: English
Classifier: Programming Language :: Python :: 3
Classifier: Programming Language :: Python :: 3.6
Classifier: Programming Language :: Python :: 3.7
Classifier: Programming Language :: Python :: 3.8
Classifier: Programming Language :: Python :: 3.9
Classifier: Programming Language :: Python :: 3
Classifier: License :: OSI Approved :: MIT License
Classifier: Operating System :: OS Independent
Requires-Python: >=3.6, <4
License-File: LICENSE
Requires-Dist: coloredlogs==15.0.1
Requires-Dist: elasticsearch<8
Requires-Dist: gfal2-python==1.12.2
Requires-Dist: psycopg2-binary
Requires-Dist: PyYAML==6.0
Requires-Dist: rucio==1.30.5
Requires-Dist: rucio-clients==1.30.2
Requires-Dist: tqdm
Requires-Dist: wheel
Requires-Dist: pandas
Requires-Dist: setuptools
Provides-Extra: dev
Requires-Dist: pre-commit; extra == "dev"
Requires-Dist: pytest; extra == "dev"
Requires-Dist: pytest-mock; extra == "dev"
